{
	"cate":[
		{"src":"../public/img/portfolio/1.png",
		 "category":"馓子这道面食据传有一千多年的历史，回族擅长炸制馓子，并且十分钟爱这道美食。",
		 "project":"每逢开斋节、古尔邦节等民族节日，回族家庭都炸馓子招待客人，馈赠邻里。"},
		 {"src":"../public/img/portfolio/2.png",
		 "category":"辣糊糊是呈现的一种糊糊的状态，香辣粘稠。",
		 "project":"在吃的时候，底料是会附着在食物上面的，在味道上又增加上了黏糊糊的口感。"},
		 {"src":"../public/img/portfolio/3.png",
		 "category":"宁夏特有的滩羊，肉质细嫩，肥瘦相间，不膻不腻，味道鲜美。",
		 "project":"2018年9月，被评为“中国菜”之宁夏十大经典名菜。"},
		 {"src":"../public/img/portfolio/4.png",
		 "category":"黄河鲶鱼是宁夏的特产，黄河水在宁夏境内平稳缓慢，这给鱼类等水产提供了良好栖息环境，故水产资源十分丰富，黄河鲶鱼就是其中最有名的。",
		 "project":"西北人最淳朴的烹饪手法，将大块的黄河鲶鱼炖的汤浓味美、肉质细嫩。"}
	]
}